pd/__init__.py
pd/__main__.py
pd/version.py
pd/__model__/__init__.py
pd/__model__/model.py
pd/__model__/utils.py
pd/aws/__init__.py
pd/aws/aws.py
pd/config/__init__.py
pd/config/config.py
pd/config/templates/zshrc.j2
pd/conv/__init__.py
pd/conv/audio.py
pd/conv/conv.py
pd/conv/conv_test.py
pd/conv/epub.py
pd/conv/text.py
pd/conv/video.py
pd/down/__init__.py
pd/down/down.py
pd/down/libgen.py
pd/down/youtube.py
pd/edit/__init__.py
pd/edit/edit.py
pd/env/__init__.py
pd/env/env.py
pd/gen/__init__.py
pd/gen/gen.py
pd/init/__init__.py
pd/init/init.py
pd/init/templates/__init__.py
pd/init/templates/pd-electron/.gitignore
pd/init/templates/pd-electron/README.md
pd/init/templates/pd-electron/forge.config.ts
pd/init/templates/pd-electron/package-lock.json
pd/init/templates/pd-electron/package.json
pd/init/templates/pd-electron/tsconfig.json
pd/init/templates/pd-electron/webpack.ts
pd/init/templates/pd-electron/yarn.lock
pd/init/templates/pd-electron/assets/icon.icns
pd/init/templates/pd-electron/assets/icon.png
pd/init/templates/pd-electron/assets/fonts/Rosario-Regular.ttf
pd/init/templates/pd-electron/assets/img/pd.png
pd/init/templates/pd-electron/src/App.tsx
pd/init/templates/pd-electron/src/Home.tsx
pd/init/templates/pd-electron/src/global.d.ts
pd/init/templates/pd-electron/src/images.d.ts
pd/init/templates/pd-electron/src/index.css
pd/init/templates/pd-electron/src/index.html
pd/init/templates/pd-electron/src/main.ts
pd/init/templates/pd-electron/src/preload.ts
pd/init/templates/pd-electron/src/renderer.tsx
pd/init/templates/pd-fastapi/.DS_Store
pd/init/templates/pd-fastapi/.gitignore
pd/init/templates/pd-fastapi/.python-version
pd/init/templates/pd-fastapi/README.md
pd/init/templates/pd-fastapi/__init__.py
pd/init/templates/pd-fastapi/package-lock.json
pd/init/templates/pd-fastapi/package.json
pd/init/templates/pd-fastapi/postcss.config.js
pd/init/templates/pd-fastapi/requirements.txt
pd/init/templates/pd-fastapi/tailwind.config.js
zf_pd-1.1.0.dist-info/LICENSE
zf_pd-1.1.0.dist-info/METADATA
zf_pd-1.1.0.dist-info/WHEEL
zf_pd-1.1.0.dist-info/entry_points.txt
zf_pd-1.1.0.dist-info/top_level.txt
zf_pd-1.1.0.dist-info/RECORD
