Metadata-Version: 2.1
Name: zf-pd
Version: 1.1.0
Summary: pd supercharges your development workflows
Author: Zeff Muks
Author-email: zeffmuks@gmail.com
License-File: LICENSE
Requires-Dist: annotated-types==0.6.0
Requires-Dist: anyio==3.7.1
Requires-Dist: beautifulsoup4==4.12.3
Requires-Dist: boto3==1.29.7
Requires-Dist: botocore==1.32.7
Requires-Dist: bs4==0.0.2
Requires-Dist: certifi==2023.11.17
Requires-Dist: chardet==5.2.0
Requires-Dist: charset-normalizer==3.3.2
Requires-Dist: click==8.1.7
Requires-Dist: decorator==4.4.2
Requires-Dist: Deprecated==1.2.14
Requires-Dist: distro==1.9.0
Requires-Dist: docutils==0.20.1
Requires-Dist: epub2pdf==0.1.0
Requires-Dist: fastapi==0.104.1
Requires-Dist: greenlet==3.0.3
Requires-Dist: h11==0.14.0
Requires-Dist: httpcore==1.0.2
Requires-Dist: httpx==0.26.0
Requires-Dist: idna==3.6
Requires-Dist: imageio==2.33.1
Requires-Dist: imageio-ffmpeg==0.4.9
Requires-Dist: img2pdf==0.5.1
Requires-Dist: importlib-metadata==7.0.1
Requires-Dist: jaraco.classes==3.3.0
Requires-Dist: Jinja2==3.1.2
Requires-Dist: jmespath==1.0.1
Requires-Dist: keyring==24.3.0
Requires-Dist: libgen-api==1.0.1
Requires-Dist: loguru==0.6.0
Requires-Dist: lxml==5.1.0
Requires-Dist: markdown-it-py==3.0.0
Requires-Dist: MarkupSafe==2.1.3
Requires-Dist: mdurl==0.1.2
Requires-Dist: mobi==0.3.3
Requires-Dist: more-itertools==10.1.0
Requires-Dist: moviepy==1.0.3
Requires-Dist: nh3==0.2.15
Requires-Dist: numpy==1.26.2
Requires-Dist: openai==1.6.1
Requires-Dist: packaging==24.0
Requires-Dist: pikepdf==8.13.0
Requires-Dist: Pillow==10.1.0
Requires-Dist: pkginfo==1.9.6
Requires-Dist: playwright==1.45.1
Requires-Dist: proglog==0.1.10
Requires-Dist: prompt-toolkit==3.0.47
Requires-Dist: pydantic==2.5.3
Requires-Dist: pydantic-core==2.14.6
Requires-Dist: pydub==0.25.1
Requires-Dist: pyee==11.1.0
Requires-Dist: Pygments==2.17.2
Requires-Dist: PyPDF2==3.0.1
Requires-Dist: python-dateutil==2.8.2
Requires-Dist: pytube==15.0.0
Requires-Dist: pytubefix==6.8.1
Requires-Dist: readme-renderer==42.0
Requires-Dist: reportlab==4.1.0
Requires-Dist: requests==2.31.0
Requires-Dist: requests-toolbelt==1.0.0
Requires-Dist: rfc3986==2.0.0
Requires-Dist: rich==13.7.0
Requires-Dist: s3transfer==0.8.0
Requires-Dist: six==1.16.0
Requires-Dist: sniffio==1.3.0
Requires-Dist: soupsieve==2.5
Requires-Dist: starlette==0.27.0
Requires-Dist: tqdm==4.66.1
Requires-Dist: twine==4.0.2
Requires-Dist: typing-extensions==4.9.0
Requires-Dist: urllib3==2.0.7
Requires-Dist: wcwidth==0.2.13
Requires-Dist: wrapt==1.16.0
Requires-Dist: youtube-transcript-api==0.6.2
Requires-Dist: zipp==3.17.0
